s3_uploader.py
PyUpdater_S3_Plugin-4.1.2.dist-info/METADATA
PyUpdater_S3_Plugin-4.1.2.dist-info/WHEEL
PyUpdater_S3_Plugin-4.1.2.dist-info/entry_points.txt
PyUpdater_S3_Plugin-4.1.2.dist-info/top_level.txt
PyUpdater_S3_Plugin-4.1.2.dist-info/RECORD
